{
  "id": "bubble/tools/request/0.1",
  "bubbleProtocolVersion": "0.0.1",
  "type": "application-connect",
  "metadata": {
    "applicationId": "bubble/tools/0",
    "author": "Bubble Labs",
    "application": "Bubble Tools",
    "version": "0.0.1",
    "logo": "bubble:114NTF3qnsGY1jYJvXo3LXGxPYbv6n?vault=7a514K7mpzMsvqbu6Cq4rxiKDfmhCScrvtjaDS6zo1oj4mVdQSYtoXWo4b3zQ7NRgsijM4q1C4kmMP65VappzTTHtbzAc&file=11111111111111111113",
    "shortSummary": "Command line tools for Bubble developers and administrators",
    "summary": "Command line administrator tools for creating and managing bubbles, reading and writing bubble content, and interacting with SDACs and smart contracts.  NB, the private key generated by this application will have admin rights over your personas - do not allow it get into the wrong hands!",
    "purpose": "Administer all your bubbles"
  },
  "request": {
    "multiPersona": true,
    "privileges": [
      {
        "privilege": "admin"
      }
    ]
  }
}